chemical_formula/__init__.py
chemical_formula/_version.py
chemical_formula/elemental_data.py
chemical_formula/formula.py
chemical_formula-2021.7.26.dist-info/AUTHORS.rst
chemical_formula-2021.7.26.dist-info/LICENSE
chemical_formula-2021.7.26.dist-info/METADATA
chemical_formula-2021.7.26.dist-info/WHEEL
chemical_formula-2021.7.26.dist-info/top_level.txt
chemical_formula-2021.7.26.dist-info/RECORD
